{"872f5a323ffffff": {"bar": 2, "research_institute": -1, "clinic": 1, "restaurant": 18, "library": 2, "atm": -1, "vending_machine": 1, "bench": 35, "parking_space": -1, "bank": 5, "place_of_worship": 16}, "872f5a32affffff": {"bar": 11, "research_institute": -1, "clinic": 8, "restaurant": 127, "library": 4, "atm": 8, "vending_machine": 52, "bench": 18, "parking_space": -1, "bank": 10, "place_of_worship": 50}, "872f5a305ffffff": {"bar": 12, "research_institute": -1, "clinic": 9, "restaurant": 69, "library": 4, "atm": 4, "vending_machine": 26, "bench": 7, "parking_space": -1, "bank": 7, "place_of_worship": 14}, "872f5aaddffffff": {"bar": 7, "research_institute": -1, "clinic": 3, "restaurant": 108, "library": 3, "atm": 4, "vending_machine": 7, "bench": 12, "parking_space": -1, "bank": 5, "place_of_worship": 29}, "872f5a331ffffff": {"bar": 8, "research_institute": -1, "clinic": 8, "restaurant": 56, "library": 3, "atm": 6, "vending_machine": 1, "bench": 2, "parking_space": -1, "bank": 5, "place_of_worship": 22}, "872f5a329ffffff": {"bar": 40, "research_institute": -1, "clinic": 9, "restaurant": 344, "library": 1, "atm": 26, "vending_machine": 261, "bench": 79, "parking_space": 1, "bank": 13, "place_of_worship": 32}, "872f5aac8ffffff": {"bar": 1, "research_institute": -1, "clinic": 2, "restaurant": 48, "library": 2, "atm": -1, "vending_machine": 8, "bench": 16, "parking_space": -1, "bank": 5, "place_of_worship": 10}, "872f5a370ffffff": {"bar": 5, "research_institute": -1, "clinic": 2, "restaurant": 150, "library": 2, "atm": 12, "vending_machine": 17, "bench": 52, "parking_space": -1, "bank": 11, "place_of_worship": 11}, "872f5a322ffffff": {"bar": 1, "research_institute": -1, "clinic": 1, "restaurant": 21, "library": 2, "atm": 2, "vending_machine": -1, "bench": -1, "parking_space": -1, "bank": 3, "place_of_worship": 15}, "872f5a375ffffff": {"bar": 99, "research_institute": -1, "clinic": 22, "restaurant": 618, "library": 4, "atm": 18, "vending_machine": 44, "bench": 26, "parking_space": 1, "bank": 29, "place_of_worship": 26}, "872f5a36cffffff": {"bar": 1, "research_institute": -1, "clinic": -1, "restaurant": 30, "library": 2, "atm": -1, "vending_machine": 2, "bench": 2, "parking_space": -1, "bank": 3, "place_of_worship": 13}, "872f5aaceffffff": {"bar": 8, "research_institute": -1, "clinic": 3, "restaurant": 106, "library": 3, "atm": 3, "vending_machine": 9, "bench": 30, "parking_space": -1, "bank": 12, "place_of_worship": 12}, "872f5aad8ffffff": {"bar": 98, "research_institute": -1, "clinic": 6, "restaurant": 458, "library": 4, "atm": 7, "vending_machine": 48, "bench": 38, "parking_space": -1, "bank": 12, "place_of_worship": 36}, "872f5a360ffffff": {"bar": 25, "research_institute": -1, "clinic": 3, "restaurant": 132, "library": 2, "atm": 3, "vending_machine": 21, "bench": 5, "parking_space": -1, "bank": 14, "place_of_worship": 7}, "872f5a366ffffff": {"bar": 12, "research_institute": -1, "clinic": 1, "restaurant": 74, "library": 1, "atm": 5, "vending_machine": 26, "bench": 43, "parking_space": -1, "bank": 3, "place_of_worship": 7}, "872f5bc8bffffff": {"bar": 1, "research_institute": -1, "clinic": 1, "restaurant": 14, "library": 1, "atm": -1, "vending_machine": 1, "bench": 1, "parking_space": -1, "bank": 3, "place_of_worship": 2}, "872f5a328ffffff": {"bar": 285, "research_institute": -1, "clinic": 31, "restaurant": 800, "library": 6, "atm": 18, "vending_machine": 777, "bench": 207, "parking_space": -1, "bank": 31, "place_of_worship": 56}, "872f5a31cffffff": {"bar": 3, "research_institute": -1, "clinic": 3, "restaurant": 37, "library": 1, "atm": 1, "vending_machine": -1, "bench": 8, "parking_space": -1, "bank": 6, "place_of_worship": 27}, "872f5a373ffffff": {"bar": 1, "research_institute": -1, "clinic": 3, "restaurant": 40, "library": 2, "atm": 3, "vending_machine": 4, "bench": -1, "parking_space": -1, "bank": 4, "place_of_worship": 9}, "872f5a35effffff": {"bar": 2, "research_institute": -1, "clinic": 5, "restaurant": 28, "library": 1, "atm": -1, "vending_machine": 13, "bench": 17, "parking_space": -1, "bank": 4, "place_of_worship": 8}, "872f5aac9ffffff": {"bar": 7, "research_institute": -1, "clinic": 11, "restaurant": 88, "library": 1, "atm": 5, "vending_machine": 1, "bench": 7, "parking_space": -1, "bank": 11, "place_of_worship": 13}, "872f5bc16ffffff": {"bar": 3, "research_institute": -1, "clinic": 4, "restaurant": 17, "library": 1, "atm": 3, "vending_machine": 26, "bench": 6, "parking_space": -1, "bank": 3, "place_of_worship": 11}, "872f5a376ffffff": {"bar": 3, "research_institute": -1, "clinic": 2, "restaurant": 57, "library": 4, "atm": 6, "vending_machine": 59, "bench": 42, "parking_space": -1, "bank": 5, "place_of_worship": 15}, "872f5a324ffffff": {"bar": -1, "research_institute": -1, "clinic": 1, "restaurant": 12, "library": 1, "atm": -1, "vending_machine": -1, "bench": 5, "parking_space": -1, "bank": 2, "place_of_worship": 12}, "872f5a309ffffff": {"bar": 17, "research_institute": 1, "clinic": 11, "restaurant": 108, "library": 3, "atm": 7, "vending_machine": 240, "bench": 25, "parking_space": -1, "bank": 3, "place_of_worship": 11}, "872f5bd90ffffff": {"bar": 1, "research_institute": -1, "clinic": 2, "restaurant": 33, "library": 2, "atm": 1, "vending_machine": 13, "bench": 11, "parking_space": -1, "bank": 12, "place_of_worship": 13}, "872f5a34cffffff": {"bar": 8, "research_institute": -1, "clinic": 10, "restaurant": 101, "library": 2, "atm": 4, "vending_machine": 14, "bench": 2, "parking_space": -1, "bank": 4, "place_of_worship": 15}, "872f5a344ffffff": {"bar": 32, "research_institute": -1, "clinic": 5, "restaurant": 312, "library": 2, "atm": 9, "vending_machine": 56, "bench": 31, "parking_space": 1, "bank": 23, "place_of_worship": 31}, "872f5bc9affffff": {"bar": -1, "research_institute": -1, "clinic": -1, "restaurant": 5, "library": 1, "atm": -1, "vending_machine": -1, "bench": 2, "parking_space": -1, "bank": 1, "place_of_worship": 2}, "872f5aad3ffffff": {"bar": 10, "research_institute": -1, "clinic": 4, "restaurant": 141, "library": -1, "atm": 5, "vending_machine": 11, "bench": 37, "parking_space": -1, "bank": 12, "place_of_worship": 13}, "872f5a362ffffff": {"bar": 13, "research_institute": -1, "clinic": -1, "restaurant": 102, "library": 3, "atm": 3, "vending_machine": 13, "bench": 9, "parking_space": -1, "bank": 11, "place_of_worship": 8}, "872f5aac1ffffff": {"bar": 2, "research_institute": -1, "clinic": 2, "restaurant": 50, "library": -1, "atm": 6, "vending_machine": 4, "bench": 14, "parking_space": -1, "bank": 6, "place_of_worship": 15}, "872f5a32effffff": {"bar": 38, "research_institute": -1, "clinic": 1, "restaurant": 415, "library": 2, "atm": -1, "vending_machine": 201, "bench": 47, "parking_space": 2, "bank": 16, "place_of_worship": 96}, "872f5a343ffffff": {"bar": 1, "research_institute": -1, "clinic": -1, "restaurant": 14, "library": -1, "atm": 2, "vending_machine": -1, "bench": 7, "parking_space": -1, "bank": 1, "place_of_worship": 2}, "872f5a325ffffff": {"bar": 1, "research_institute": -1, "clinic": 2, "restaurant": 18, "library": 2, "atm": 1, "vending_machine": 5, "bench": -1, "parking_space": 1, "bank": 2, "place_of_worship": 7}, "872f5bc82ffffff": {"bar": 15, "research_institute": 1, "clinic": 7, "restaurant": 46, "library": 4, "atm": -1, "vending_machine": -1, "bench": 4, "parking_space": -1, "bank": 5, "place_of_worship": 3}, "872f5a30cffffff": {"bar": -1, "research_institute": -1, "clinic": 2, "restaurant": 51, "library": 4, "atm": 1, "vending_machine": 14, "bench": 2, "parking_space": -1, "bank": 8, "place_of_worship": 12}, "872f5bc89ffffff": {"bar": -1, "research_institute": -1, "clinic": 2, "restaurant": 24, "library": -1, "atm": 1, "vending_machine": 10, "bench": 7, "parking_space": 1, "bank": -1, "place_of_worship": 3}, "872f5bcb0ffffff": {"bar": -1, "research_institute": -1, "clinic": -1, "restaurant": 10, "library": 1, "atm": -1, "vending_machine": 1, "bench": 14, "parking_space": -1, "bank": -1, "place_of_worship": 5}, "872f5a26dffffff": {"bar": 1, "research_institute": -1, "clinic": 4, "restaurant": 18, "library": -1, "atm": -1, "vending_machine": 11, "bench": -1, "parking_space": -1, "bank": 2, "place_of_worship": 2}, "872f5a32bffffff": {"bar": 4, "research_institute": -1, "clinic": 6, "restaurant": 98, "library": 5, "atm": 2, "vending_machine": 26, "bench": 148, "parking_space": -1, "bank": 11, "place_of_worship": 60}, "872f5bcc1ffffff": {"bar": -1, "research_institute": -1, "clinic": 1, "restaurant": 28, "library": -1, "atm": 3, "vending_machine": 30, "bench": 1, "parking_space": -1, "bank": -1, "place_of_worship": 6}, "872f5aadbffffff": {"bar": 15, "research_institute": -1, "clinic": -1, "restaurant": 151, "library": 2, "atm": 6, "vending_machine": 37, "bench": 69, "parking_space": -1, "bank": 5, "place_of_worship": 23}, "872f5a334ffffff": {"bar": 8, "research_institute": -1, "clinic": 3, "restaurant": 64, "library": -1, "atm": 5, "vending_machine": -1, "bench": -1, "parking_space": -1, "bank": 6, "place_of_worship": 26}, "872f5aad2ffffff": {"bar": 5, "research_institute": -1, "clinic": 3, "restaurant": 67, "library": 2, "atm": 5, "vending_machine": 26, "bench": 96, "parking_space": 14, "bank": -1, "place_of_worship": 34}, "872f5a364ffffff": {"bar": 30, "research_institute": -1, "clinic": 8, "restaurant": 217, "library": 1, "atm": 1, "vending_machine": 43, "bench": 27, "parking_space": 2, "bank": 6, "place_of_worship": 12}, "872f5a345ffffff": {"bar": 26, "research_institute": -1, "clinic": 1, "restaurant": 183, "library": 3, "atm": 5, "vending_machine": 3, "bench": 18, "parking_space": -1, "bank": 6, "place_of_worship": 17}, "872f5a340ffffff": {"bar": 5, "research_institute": -1, "clinic": -1, "restaurant": 59, "library": 2, "atm": -1, "vending_machine": 2, "bench": 1, "parking_space": -1, "bank": 5, "place_of_worship": 5}, "872f5a346ffffff": {"bar": 2, "research_institute": -1, "clinic": 2, "restaurant": 48, "library": 2, "atm": 2, "vending_machine": 5, "bench": 20, "parking_space": -1, "bank": 5, "place_of_worship": 16}, "872f5a326ffffff": {"bar": 1, "research_institute": -1, "clinic": -1, "restaurant": 18, "library": 3, "atm": -1, "vending_machine": -1, "bench": 4, "parking_space": 1, "bank": -1, "place_of_worship": 11}, "872f5a34dffffff": {"bar": 17, "research_institute": -1, "clinic": 8, "restaurant": 124, "library": 2, "atm": 2, "vending_machine": 22, "bench": 10, "parking_space": -1, "bank": 12, "place_of_worship": 10}, "872f5bdb6ffffff": {"bar": 1, "research_institute": -1, "clinic": -1, "restaurant": 13, "library": -1, "atm": 1, "vending_machine": 2, "bench": 9, "parking_space": 6, "bank": 5, "place_of_worship": 18}, "872f5a30dffffff": {"bar": 5, "research_institute": -1, "clinic": 7, "restaurant": 50, "library": 2, "atm": 1, "vending_machine": 108, "bench": 30, "parking_space": -1, "bank": 8, "place_of_worship": 35}, "872f5bc15ffffff": {"bar": 1, "research_institute": -1, "clinic": -1, "restaurant": 15, "library": -1, "atm": 2, "vending_machine": 2, "bench": 6, "parking_space": -1, "bank": 2, "place_of_worship": 6}, "872f5a333ffffff": {"bar": 11, "research_institute": -1, "clinic": 3, "restaurant": 53, "library": 1, "atm": 1, "vending_machine": 6, "bench": -1, "parking_space": -1, "bank": 6, "place_of_worship": 16}, "872f5a350ffffff": {"bar": -1, "research_institute": -1, "clinic": 5, "restaurant": 15, "library": 1, "atm": 2, "vending_machine": 4, "bench": -1, "parking_space": -1, "bank": 3, "place_of_worship": 7}, "872f5a269ffffff": {"bar": 1, "research_institute": -1, "clinic": -1, "restaurant": 4, "library": 1, "atm": -1, "vending_machine": 11, "bench": -1, "parking_space": -1, "bank": -1, "place_of_worship": 7}, "872f5a354ffffff": {"bar": -1, "research_institute": -1, "clinic": 3, "restaurant": 22, "library": 1, "atm": -1, "vending_machine": 21, "bench": 3, "parking_space": -1, "bank": 7, "place_of_worship": 6}, "872f5b529ffffff": {"bar": 1, "research_institute": -1, "clinic": 4, "restaurant": 23, "library": 1, "atm": 1, "vending_machine": -1, "bench": -1, "parking_space": -1, "bank": 4, "place_of_worship": 2}, "872f5aacaffffff": {"bar": 23, "research_institute": -1, "clinic": -1, "restaurant": 129, "library": 2, "atm": 8, "vending_machine": 24, "bench": 18, "parking_space": 1, "bank": 9, "place_of_worship": 11}, "872f5bc1affffff": {"bar": -1, "research_institute": -1, "clinic": -1, "restaurant": -1, "library": -1, "atm": -1, "vending_machine": -1, "bench": 2, "parking_space": -1, "bank": -1, "place_of_worship": 4}, "872f5a363ffffff": {"bar": 2, "research_institute": -1, "clinic": 3, "restaurant": 38, "library": 2, "atm": 2, "vending_machine": 9, "bench": 4, "parking_space": -1, "bank": 5, "place_of_worship": 10}, "872f5a365ffffff": {"bar": 10, "research_institute": -1, "clinic": -1, "restaurant": 116, "library": 2, "atm": 3, "vending_machine": 21, "bench": -1, "parking_space": -1, "bank": 13, "place_of_worship": 17}, "872f5bc90ffffff": {"bar": -1, "research_institute": -1, "clinic": -1, "restaurant": 24, "library": 2, "atm": 3, "vending_machine": -1, "bench": 4, "parking_space": -1, "bank": 2, "place_of_worship": 3}, "872f5a320ffffff": {"bar": 3, "research_institute": -1, "clinic": 1, "restaurant": 21, "library": 1, "atm": -1, "vending_machine": -1, "bench": -1, "parking_space": -1, "bank": 6, "place_of_worship": 12}, "872f5a303ffffff": {"bar": 11, "research_institute": -1, "clinic": 5, "restaurant": 44, "library": 1, "atm": 3, "vending_machine": 2, "bench": 2, "parking_space": -1, "bank": 8, "place_of_worship": 18}, "872f5aadcffffff": {"bar": 20, "research_institute": -1, "clinic": 2, "restaurant": 218, "library": 3, "atm": 10, "vending_machine": 79, "bench": 97, "parking_space": -1, "bank": 13, "place_of_worship": 14}, "872f5a372ffffff": {"bar": 12, "research_institute": -1, "clinic": 3, "restaurant": 195, "library": 2, "atm": 4, "vending_machine": 7, "bench": 5, "parking_space": -1, "bank": 28, "place_of_worship": 19}, "872f5bc8dffffff": {"bar": -1, "research_institute": -1, "clinic": 1, "restaurant": 10, "library": -1, "atm": 1, "vending_machine": -1, "bench": 3, "parking_space": -1, "bank": 1, "place_of_worship": 3}, "872f5a32cffffff": {"bar": 34, "research_institute": -1, "clinic": 3, "restaurant": 310, "library": 2, "atm": 6, "vending_machine": 414, "bench": 80, "parking_space": -1, "bank": 15, "place_of_worship": 21}, "872f5bcb1ffffff": {"bar": 2, "research_institute": -1, "clinic": -1, "restaurant": 20, "library": 2, "atm": -1, "vending_machine": 2, "bench": 15, "parking_space": -1, "bank": 2, "place_of_worship": 11}, "872f5a32dffffff": {"bar": 66, "research_institute": -1, "clinic": 15, "restaurant": 538, "library": 2, "atm": 27, "vending_machine": 226, "bench": 67, "parking_space": 7, "bank": 50, "place_of_worship": 8}, "872f5aad9ffffff": {"bar": 67, "research_institute": -1, "clinic": 11, "restaurant": 382, "library": 2, "atm": 4, "vending_machine": 39, "bench": 13, "parking_space": 2, "bank": 13, "place_of_worship": 21}, "872f5a321ffffff": {"bar": 19, "research_institute": -1, "clinic": 2, "restaurant": 132, "library": -1, "atm": 5, "vending_machine": 69, "bench": 28, "parking_space": -1, "bank": 14, "place_of_worship": 24}, "872f5aadeffffff": {"bar": 42, "research_institute": -1, "clinic": 8, "restaurant": 488, "library": 2, "atm": 14, "vending_machine": 23, "bench": 85, "parking_space": -1, "bank": 35, "place_of_worship": 25}, "872f5aad1ffffff": {"bar": 1, "research_institute": -1, "clinic": -1, "restaurant": 49, "library": 1, "atm": -1, "vending_machine": 4, "bench": 10, "parking_space": -1, "bank": 1, "place_of_worship": 5}, "872f5bc10ffffff": {"bar": 1, "research_institute": -1, "clinic": 1, "restaurant": 18, "library": -1, "atm": -1, "vending_machine": -1, "bench": 14, "parking_space": -1, "bank": 1, "place_of_worship": 5}, "872f5a335ffffff": {"bar": -1, "research_institute": -1, "clinic": 1, "restaurant": 11, "library": -1, "atm": -1, "vending_machine": -1, "bench": -1, "parking_space": -1, "bank": 5, "place_of_worship": 19}, "872f5bca8ffffff": {"bar": 1, "research_institute": -1, "clinic": 2, "restaurant": 23, "library": -1, "atm": 2, "vending_machine": -1, "bench": -1, "parking_space": -1, "bank": -1, "place_of_worship": 1}, "872f5aaccffffff": {"bar": 5, "research_institute": -1, "clinic": -1, "restaurant": 41, "library": 3, "atm": 8, "vending_machine": 38, "bench": 18, "parking_space": 4, "bank": 11, "place_of_worship": 13}, "872f5a371ffffff": {"bar": 11, "research_institute": -1, "clinic": 2, "restaurant": 126, "library": 4, "atm": 6, "vending_machine": 27, "bench": 19, "parking_space": -1, "bank": 6, "place_of_worship": 33}, "872f5bd98ffffff": {"bar": 4, "research_institute": -1, "clinic": 14, "restaurant": 42, "library": 1, "atm": 1, "vending_machine": 6, "bench": 5, "parking_space": -1, "bank": 3, "place_of_worship": 10}, "872f5bcabffffff": {"bar": -1, "research_institute": -1, "clinic": 2, "restaurant": 5, "library": -1, "atm": 1, "vending_machine": -1, "bench": 2, "parking_space": 1, "bank": 2, "place_of_worship": 2}, "872f5bcb4ffffff": {"bar": 7, "research_institute": -1, "clinic": 3, "restaurant": 48, "library": 2, "atm": 1, "vending_machine": 16, "bench": -1, "parking_space": -1, "bank": 1, "place_of_worship": 9}, "872f5bcb5ffffff": {"bar": 11, "research_institute": -1, "clinic": 1, "restaurant": 42, "library": 3, "atm": 3, "vending_machine": 14, "bench": 4, "parking_space": -1, "bank": 1, "place_of_worship": 8}, "872f5aacbffffff": {"bar": -1, "research_institute": -1, "clinic": -1, "restaurant": 24, "library": 2, "atm": -1, "vending_machine": 5, "bench": 5, "parking_space": -1, "bank": 2, "place_of_worship": 8}, "872f5a361ffffff": {"bar": 5, "research_institute": -1, "clinic": 1, "restaurant": 86, "library": 2, "atm": 10, "vending_machine": 5, "bench": 15, "parking_space": -1, "bank": 9, "place_of_worship": 22}, "872f5bd96ffffff": {"bar": -1, "research_institute": -1, "clinic": -1, "restaurant": 25, "library": 1, "atm": -1, "vending_machine": -1, "bench": 2, "parking_space": -1, "bank": 3, "place_of_worship": 5}, "872f5aae9ffffff": {"bar": 8, "research_institute": -1, "clinic": 1, "restaurant": 46, "library": 1, "atm": 1, "vending_machine": 35, "bench": 12, "parking_space": -1, "bank": 5, "place_of_worship": 15}, "872f5a374ffffff": {"bar": 9, "research_institute": -1, "clinic": 4, "restaurant": 153, "library": 5, "atm": 6, "vending_machine": 45, "bench": 8, "parking_space": 1, "bank": 8, "place_of_worship": 42}, "872f5a30effffff": {"bar": -1, "research_institute": -1, "clinic": 5, "restaurant": 20, "library": 1, "atm": -1, "vending_machine": -1, "bench": -1, "parking_space": -1, "bank": 3, "place_of_worship": 15}, "872f5a330ffffff": {"bar": 5, "research_institute": -1, "clinic": 1, "restaurant": 42, "library": 1, "atm": 3, "vending_machine": -1, "bench": -1, "parking_space": -1, "bank": 9, "place_of_worship": 24}, "872f5a301ffffff": {"bar": 1, "research_institute": -1, "clinic": 8, "restaurant": 30, "library": 1, "atm": 1, "vending_machine": 2, "bench": -1, "parking_space": -1, "bank": 1, "place_of_worship": 11}, "872f5bc9effffff": {"bar": -1, "research_institute": -1, "clinic": -1, "restaurant": 18, "library": 2, "atm": -1, "vending_machine": -1, "bench": -1, "parking_space": -1, "bank": -1, "place_of_worship": -1}, "872f5bcceffffff": {"bar": -1, "research_institute": -1, "clinic": -1, "restaurant": 1, "library": -1, "atm": -1, "vending_machine": 14, "bench": 27, "parking_space": -1, "bank": -1, "place_of_worship": 3}, "872f5a368ffffff": {"bar": 13, "research_institute": -1, "clinic": 5, "restaurant": 75, "library": 2, "atm": 3, "vending_machine": 5, "bench": 9, "parking_space": -1, "bank": 4, "place_of_worship": 16}, "872f5aacdffffff": {"bar": -1, "research_institute": -1, "clinic": -1, "restaurant": 19, "library": -1, "atm": 2, "vending_machine": -1, "bench": 19, "parking_space": 1, "bank": 4, "place_of_worship": 11}, "872f5a36effffff": {"bar": 5, "research_institute": -1, "clinic": 4, "restaurant": 72, "library": 2, "atm": 8, "vending_machine": 8, "bench": 9, "parking_space": -1, "bank": 6, "place_of_worship": 12}, "872f5bd92ffffff": {"bar": 3, "research_institute": -1, "clinic": 2, "restaurant": 70, "library": 2, "atm": 3, "vending_machine": 9, "bench": -1, "parking_space": -1, "bank": 4, "place_of_worship": 9}, "872f5bd94ffffff": {"bar": -1, "research_institute": -1, "clinic": 1, "restaurant": 7, "library": 1, "atm": 1, "vending_machine": -1, "bench": 19, "parking_space": -1, "bank": 5, "place_of_worship": 11}, "872f5a300ffffff": {"bar": 4, "research_institute": -1, "clinic": 6, "restaurant": 55, "library": 2, "atm": 3, "vending_machine": -1, "bench": 1, "parking_space": -1, "bank": 8, "place_of_worship": 7}, "872f5aa98ffffff": {"bar": 2, "research_institute": -1, "clinic": 6, "restaurant": 23, "library": 1, "atm": 5, "vending_machine": -1, "bench": 11, "parking_space": -1, "bank": 6, "place_of_worship": 4}, "872f5a308ffffff": {"bar": 4, "research_institute": -1, "clinic": 11, "restaurant": 46, "library": 2, "atm": 1, "vending_machine": 505, "bench": 17, "parking_space": -1, "bank": 9, "place_of_worship": 11}, "872f5bcb3ffffff": {"bar": -1, "research_institute": -1, "clinic": -1, "restaurant": 14, "library": 1, "atm": 4, "vending_machine": 2, "bench": 7, "parking_space": -1, "bank": 1, "place_of_worship": 4}, "872f5a34bffffff": {"bar": -1, "research_institute": -1, "clinic": -1, "restaurant": 6, "library": -1, "atm": -1, "vending_machine": -1, "bench": -1, "parking_space": -1, "bank": -1, "place_of_worship": 6}, "872f5a31dffffff": {"bar": 2, "research_institute": -1, "clinic": 5, "restaurant": 13, "library": -1, "atm": -1, "vending_machine": 3, "bench": 12, "parking_space": -1, "bank": 3, "place_of_worship": 6}, "872f5aaecffffff": {"bar": 1, "research_institute": -1, "clinic": -1, "restaurant": 14, "library": -1, "atm": 4, "vending_machine": 6, "bench": 32, "parking_space": -1, "bank": 3, "place_of_worship": 3}, "872f5a304ffffff": {"bar": 3, "research_institute": -1, "clinic": 6, "restaurant": 44, "library": -1, "atm": 1, "vending_machine": -1, "bench": -1, "parking_space": -1, "bank": 8, "place_of_worship": 19}, "872f5aaeaffffff": {"bar": 26, "research_institute": -1, "clinic": 2, "restaurant": 75, "library": 2, "atm": 13, "vending_machine": 44, "bench": 34, "parking_space": 2, "bank": 9, "place_of_worship": 15}, "872f5aae8ffffff": {"bar": 9, "research_institute": -1, "clinic": 5, "restaurant": 60, "library": -1, "atm": 2, "vending_machine": 50, "bench": 23, "parking_space": -1, "bank": 6, "place_of_worship": 14}, "872f5bcb2ffffff": {"bar": 2, "research_institute": -1, "clinic": -1, "restaurant": 25, "library": -1, "atm": 3, "vending_machine": 26, "bench": 12, "parking_space": -1, "bank": 6, "place_of_worship": 9}, "872f5bc18ffffff": {"bar": -1, "research_institute": -1, "clinic": 1, "restaurant": 11, "library": -1, "atm": -1, "vending_machine": -1, "bench": 8, "parking_space": -1, "bank": 1, "place_of_worship": 8}, "872f5aaebffffff": {"bar": -1, "research_institute": -1, "clinic": 1, "restaurant": 52, "library": 1, "atm": 4, "vending_machine": 40, "bench": 22, "parking_space": 3, "bank": 6, "place_of_worship": 27}, "872f5a341ffffff": {"bar": 7, "research_institute": -1, "clinic": 3, "restaurant": 94, "library": 3, "atm": 1, "vending_machine": 2, "bench": 4, "parking_space": -1, "bank": 9, "place_of_worship": 7}, "872f5a35cffffff": {"bar": 2, "research_institute": -1, "clinic": 5, "restaurant": 26, "library": 1, "atm": 1, "vending_machine": 2, "bench": 12, "parking_space": -1, "bank": 2, "place_of_worship": 9}, "872f5b56affffff": {"bar": -1, "research_institute": -1, "clinic": -1, "restaurant": 1, "library": 1, "atm": -1, "vending_machine": 1, "bench": -1, "parking_space": -1, "bank": -1, "place_of_worship": -1}, "872f5aac3ffffff": {"bar": 7, "research_institute": -1, "clinic": 2, "restaurant": 44, "library": 2, "atm": 3, "vending_machine": 25, "bench": 10, "parking_space": -1, "bank": 1, "place_of_worship": 6}, "872f5aa99ffffff": {"bar": 3, "research_institute": -1, "clinic": 1, "restaurant": 19, "library": 1, "atm": -1, "vending_machine": -1, "bench": -1, "parking_space": -1, "bank": 2, "place_of_worship": 15}, "872f5aa8bffffff": {"bar": -1, "research_institute": -1, "clinic": 1, "restaurant": 8, "library": -1, "atm": 2, "vending_machine": -1, "bench": -1, "parking_space": -1, "bank": 1, "place_of_worship": 2}, "872f5bcddffffff": {"bar": -1, "research_institute": -1, "clinic": -1, "restaurant": 8, "library": 1, "atm": -1, "vending_machine": 78, "bench": 29, "parking_space": -1, "bank": -1, "place_of_worship": 2}, "872f5a348ffffff": {"bar": -1, "research_institute": -1, "clinic": 3, "restaurant": 20, "library": -1, "atm": 1, "vending_machine": 4, "bench": 2, "parking_space": -1, "bank": 2, "place_of_worship": 4}, "872f5a36affffff": {"bar": 3, "research_institute": -1, "clinic": 7, "restaurant": 61, "library": 1, "atm": 4, "vending_machine": 1, "bench": 21, "parking_space": -1, "bank": 2, "place_of_worship": 7}, "872f5b509ffffff": {"bar": 4, "research_institute": -1, "clinic": 5, "restaurant": 20, "library": 2, "atm": 1, "vending_machine": 7, "bench": 5, "parking_space": -1, "bank": 5, "place_of_worship": 12}, "872f5a355ffffff": {"bar": 2, "research_institute": -1, "clinic": 1, "restaurant": 28, "library": 1, "atm": 2, "vending_machine": 2, "bench": -1, "parking_space": -1, "bank": 3, "place_of_worship": 2}, "872f5bc83ffffff": {"bar": 4, "research_institute": -1, "clinic": 12, "restaurant": 55, "library": 1, "atm": 3, "vending_machine": 3, "bench": 9, "parking_space": -1, "bank": 7, "place_of_worship": 2}, "872f5bdb2ffffff": {"bar": 4, "research_institute": -1, "clinic": 4, "restaurant": 49, "library": 1, "atm": 6, "vending_machine": 15, "bench": 13, "parking_space": 7, "bank": 5, "place_of_worship": 5}, "872f5aadaffffff": {"bar": 42, "research_institute": -1, "clinic": 5, "restaurant": 216, "library": 3, "atm": 8, "vending_machine": 33, "bench": 22, "parking_space": -1, "bank": 8, "place_of_worship": 7}, "872f5aa8affffff": {"bar": -1, "research_institute": -1, "clinic": -1, "restaurant": 30, "library": 1, "atm": 1, "vending_machine": -1, "bench": -1, "parking_space": -1, "bank": 2, "place_of_worship": 19}, "872f5bcb6ffffff": {"bar": -1, "research_institute": -1, "clinic": 4, "restaurant": 38, "library": 3, "atm": 4, "vending_machine": 20, "bench": 14, "parking_space": -1, "bank": 2, "place_of_worship": 4}, "872f5aa88ffffff": {"bar": 11, "research_institute": -1, "clinic": 4, "restaurant": 42, "library": 1, "atm": 3, "vending_machine": 16, "bench": 8, "parking_space": -1, "bank": 3, "place_of_worship": 2}, "872f5aa5affffff": {"bar": 2, "research_institute": -1, "clinic": 6, "restaurant": 105, "library": 1, "atm": 10, "vending_machine": 74, "bench": 13, "parking_space": 3, "bank": 3, "place_of_worship": 7}, "872f5a30affffff": {"bar": -1, "research_institute": -1, "clinic": 2, "restaurant": 11, "library": -1, "atm": -1, "vending_machine": 15, "bench": -1, "parking_space": -1, "bank": 1, "place_of_worship": 9}, "872f5bc86ffffff": {"bar": 1, "research_institute": -1, "clinic": -1, "restaurant": 15, "library": 2, "atm": -1, "vending_machine": 2, "bench": 6, "parking_space": -1, "bank": 1, "place_of_worship": 5}, "872f5bd9affffff": {"bar": 1, "research_institute": -1, "clinic": 1, "restaurant": 46, "library": 5, "atm": 3, "vending_machine": 17, "bench": -1, "parking_space": 1, "bank": 2, "place_of_worship": 7}, "872f5a225ffffff": {"bar": -1, "research_institute": -1, "clinic": -1, "restaurant": 7, "library": 2, "atm": -1, "vending_machine": 14, "bench": -1, "parking_space": -1, "bank": 2, "place_of_worship": 2}, "872f5b55bffffff": {"bar": -1, "research_institute": -1, "clinic": -1, "restaurant": 3, "library": -1, "atm": -1, "vending_machine": 1, "bench": -1, "parking_space": -1, "bank": -1, "place_of_worship": 1}, "872f5b52affffff": {"bar": 4, "research_institute": -1, "clinic": 5, "restaurant": 52, "library": 1, "atm": 9, "vending_machine": 23, "bench": 10, "parking_space": -1, "bank": 6, "place_of_worship": 8}, "872f5b524ffffff": {"bar": -1, "research_institute": -1, "clinic": -1, "restaurant": 2, "library": 1, "atm": 1, "vending_machine": 1, "bench": -1, "parking_space": -1, "bank": 1, "place_of_worship": 4}, "872f5bcc0ffffff": {"bar": 3, "research_institute": -1, "clinic": -1, "restaurant": 13, "library": -1, "atm": 1, "vending_machine": -1, "bench": -1, "parking_space": -1, "bank": 1, "place_of_worship": 2}, "872f5a34affffff": {"bar": -1, "research_institute": -1, "clinic": 6, "restaurant": 23, "library": -1, "atm": 1, "vending_machine": 3, "bench": -1, "parking_space": -1, "bank": 5, "place_of_worship": 4}, "872f5a356ffffff": {"bar": -1, "research_institute": -1, "clinic": 4, "restaurant": 14, "library": 2, "atm": 2, "vending_machine": 20, "bench": -1, "parking_space": -1, "bank": 2, "place_of_worship": 13}, "872f5a342ffffff": {"bar": 1, "research_institute": -1, "clinic": 1, "restaurant": 72, "library": 2, "atm": 1, "vending_machine": 3, "bench": 32, "parking_space": -1, "bank": 5, "place_of_worship": 9}, "872f5a349ffffff": {"bar": 1, "research_institute": -1, "clinic": 1, "restaurant": 29, "library": 1, "atm": 2, "vending_machine": 32, "bench": 17, "parking_space": -1, "bank": 2, "place_of_worship": 1}, "872f5bd9effffff": {"bar": -1, "research_institute": -1, "clinic": -1, "restaurant": 16, "library": -1, "atm": 1, "vending_machine": 19, "bench": 5, "parking_space": -1, "bank": 2, "place_of_worship": 15}, "872f5a30bffffff": {"bar": 6, "research_institute": -1, "clinic": 9, "restaurant": 70, "library": 1, "atm": 3, "vending_machine": 356, "bench": 20, "parking_space": 1, "bank": 6, "place_of_worship": 19}, "872f5bcf6ffffff": {"bar": -1, "research_institute": -1, "clinic": -1, "restaurant": 1, "library": -1, "atm": -1, "vending_machine": -1, "bench": 9, "parking_space": -1, "bank": -1, "place_of_worship": 3}, "872f5aad6ffffff": {"bar": -1, "research_institute": -1, "clinic": 2, "restaurant": 8, "library": -1, "atm": 1, "vending_machine": 5, "bench": -1, "parking_space": -1, "bank": 3, "place_of_worship": -1}, "872f5b535ffffff": {"bar": -1, "research_institute": -1, "clinic": -1, "restaurant": -1, "library": 1, "atm": -1, "vending_machine": 6, "bench": 1, "parking_space": -1, "bank": -1, "place_of_worship": 7}, "872f5a351ffffff": {"bar": 20, "research_institute": -1, "clinic": 9, "restaurant": 72, "library": -1, "atm": 2, "vending_machine": 18, "bench": 14, "parking_space": -1, "bank": 6, "place_of_worship": 3}, "872f5a369ffffff": {"bar": 8, "research_institute": -1, "clinic": -1, "restaurant": 51, "library": 1, "atm": 3, "vending_machine": 1, "bench": -1, "parking_space": -1, "bank": 4, "place_of_worship": 17}, "872f5a260ffffff": {"bar": -1, "research_institute": -1, "clinic": -1, "restaurant": 1, "library": -1, "atm": -1, "vending_machine": -1, "bench": -1, "parking_space": -1, "bank": -1, "place_of_worship": -1}, "872f5bcc2ffffff": {"bar": 9, "research_institute": -1, "clinic": 2, "restaurant": 32, "library": 1, "atm": 3, "vending_machine": 40, "bench": -1, "parking_space": 1, "bank": 5, "place_of_worship": 8}, "872f5aa9bffffff": {"bar": -1, "research_institute": -1, "clinic": -1, "restaurant": 4, "library": 1, "atm": -1, "vending_machine": -1, "bench": -1, "parking_space": -1, "bank": -1, "place_of_worship": 13}, "872f5a306ffffff": {"bar": 16, "research_institute": -1, "clinic": 5, "restaurant": 56, "library": 1, "atm": 1, "vending_machine": 2, "bench": 1, "parking_space": -1, "bank": 10, "place_of_worship": 14}, "872f5a352ffffff": {"bar": 1, "research_institute": -1, "clinic": 4, "restaurant": 10, "library": 1, "atm": 1, "vending_machine": 17, "bench": 5, "parking_space": -1, "bank": 3, "place_of_worship": 3}, "872f5a353ffffff": {"bar": -1, "research_institute": -1, "clinic": 4, "restaurant": 10, "library": 1, "atm": -1, "vending_machine": 3, "bench": 2, "parking_space": -1, "bank": 4, "place_of_worship": 5}, "872f5a359ffffff": {"bar": -1, "research_institute": -1, "clinic": 2, "restaurant": 9, "library": 1, "atm": 1, "vending_machine": 3, "bench": -1, "parking_space": -1, "bank": 4, "place_of_worship": 3}, "872f5aa9dffffff": {"bar": -1, "research_institute": -1, "clinic": 1, "restaurant": 14, "library": 2, "atm": 1, "vending_machine": -1, "bench": 7, "parking_space": -1, "bank": 1, "place_of_worship": 14}, "872f5bc8affffff": {"bar": 9, "research_institute": -1, "clinic": 8, "restaurant": 84, "library": 3, "atm": 4, "vending_machine": 40, "bench": 1, "parking_space": -1, "bank": 13, "place_of_worship": 4}, "872f5bc88ffffff": {"bar": -1, "research_institute": -1, "clinic": -1, "restaurant": 15, "library": 2, "atm": 1, "vending_machine": 3, "bench": 8, "parking_space": -1, "bank": -1, "place_of_worship": 3}, "872f5a31effffff": {"bar": 3, "research_institute": -1, "clinic": 2, "restaurant": 16, "library": -1, "atm": 1, "vending_machine": 2, "bench": 1, "parking_space": -1, "bank": 5, "place_of_worship": 8}, "872f5b424ffffff": {"bar": -1, "research_institute": -1, "clinic": -1, "restaurant": -1, "library": -1, "atm": -1, "vending_machine": -1, "bench": -1, "parking_space": -1, "bank": 1, "place_of_worship": -1}, "872f5aa8effffff": {"bar": -1, "research_institute": -1, "clinic": -1, "restaurant": 26, "library": 3, "atm": 1, "vending_machine": 2, "bench": 1, "parking_space": -1, "bank": 8, "place_of_worship": 16}, "872f5aaedffffff": {"bar": 3, "research_institute": -1, "clinic": 1, "restaurant": 33, "library": 2, "atm": 8, "vending_machine": 36, "bench": 59, "parking_space": 1, "bank": 5, "place_of_worship": 13}, "872f5a36dffffff": {"bar": -1, "research_institute": -1, "clinic": -1, "restaurant": 13, "library": 1, "atm": -1, "vending_machine": 1, "bench": 3, "parking_space": -1, "bank": 1, "place_of_worship": 6}, "872f5bc84ffffff": {"bar": 4, "research_institute": -1, "clinic": 1, "restaurant": 36, "library": 1, "atm": 2, "vending_machine": 1, "bench": -1, "parking_space": -1, "bank": 1, "place_of_worship": 6}, "872f5bd9bffffff": {"bar": 2, "research_institute": -1, "clinic": -1, "restaurant": 27, "library": 1, "atm": 1, "vending_machine": 65, "bench": 2, "parking_space": -1, "bank": 3, "place_of_worship": 5}, "872f5bcd4ffffff": {"bar": 1, "research_institute": -1, "clinic": 1, "restaurant": 19, "library": -1, "atm": 2, "vending_machine": 24, "bench": 7, "parking_space": -1, "bank": -1, "place_of_worship": 2}, "872f5aad0ffffff": {"bar": 2, "research_institute": -1, "clinic": 1, "restaurant": 34, "library": 2, "atm": 4, "vending_machine": 3, "bench": 16, "parking_space": -1, "bank": 3, "place_of_worship": 1}, "872f5bc81ffffff": {"bar": -1, "research_institute": -1, "clinic": 4, "restaurant": 13, "library": 2, "atm": 2, "vending_machine": 2, "bench": 7, "parking_space": -1, "bank": -1, "place_of_worship": 3}, "872f5aad5ffffff": {"bar": -1, "research_institute": -1, "clinic": -1, "restaurant": 19, "library": -1, "atm": 1, "vending_machine": 13, "bench": 27, "parking_space": -1, "bank": -1, "place_of_worship": -1}, "872f5bca0ffffff": {"bar": -1, "research_institute": -1, "clinic": -1, "restaurant": 5, "library": -1, "atm": -1, "vending_machine": -1, "bench": 2, "parking_space": -1, "bank": -1, "place_of_worship": 4}, "872f5bcebffffff": {"bar": -1, "research_institute": -1, "clinic": -1, "restaurant": 3, "library": -1, "atm": -1, "vending_machine": -1, "bench": -1, "parking_space": -1, "bank": -1, "place_of_worship": 1}, "872f5bc91ffffff": {"bar": -1, "research_institute": -1, "clinic": -1, "restaurant": 10, "library": 4, "atm": -1, "vending_machine": -1, "bench": 24, "parking_space": -1, "bank": 2, "place_of_worship": 3}, "872f5bc9cffffff": {"bar": -1, "research_institute": -1, "clinic": -1, "restaurant": 11, "library": 5, "atm": 1, "vending_machine": 10, "bench": 3, "parking_space": -1, "bank": 3, "place_of_worship": 1}, "872f5b528ffffff": {"bar": -1, "research_institute": -1, "clinic": 1, "restaurant": 2, "library": 1, "atm": -1, "vending_machine": -1, "bench": -1, "parking_space": -1, "bank": 2, "place_of_worship": 3}, "872f5a35dffffff": {"bar": -1, "research_institute": -1, "clinic": 1, "restaurant": 19, "library": -1, "atm": 3, "vending_machine": 6, "bench": 2, "parking_space": -1, "bank": 3, "place_of_worship": 5}, "872f5b534ffffff": {"bar": -1, "research_institute": -1, "clinic": -1, "restaurant": 2, "library": -1, "atm": -1, "vending_machine": -1, "bench": 9, "parking_space": 2, "bank": -1, "place_of_worship": 4}, "872f5bcccffffff": {"bar": -1, "research_institute": -1, "clinic": -1, "restaurant": 6, "library": -1, "atm": 1, "vending_machine": 5, "bench": 40, "parking_space": -1, "bank": -1, "place_of_worship": 6}, "872f5bc06ffffff": {"bar": 3, "research_institute": -1, "clinic": -1, "restaurant": 53, "library": 2, "atm": 2, "vending_machine": 1, "bench": 13, "parking_space": -1, "bank": 6, "place_of_worship": 9}, "872f5bc8cffffff": {"bar": -1, "research_institute": -1, "clinic": -1, "restaurant": 6, "library": 1, "atm": -1, "vending_machine": -1, "bench": 5, "parking_space": -1, "bank": -1, "place_of_worship": 4}, "872f5bcdcffffff": {"bar": -1, "research_institute": -1, "clinic": -1, "restaurant": 4, "library": 1, "atm": -1, "vending_machine": 39, "bench": 4, "parking_space": -1, "bank": 1, "place_of_worship": 3}, "872f5bcaeffffff": {"bar": -1, "research_institute": -1, "clinic": -1, "restaurant": 4, "library": 1, "atm": -1, "vending_machine": -1, "bench": 12, "parking_space": -1, "bank": -1, "place_of_worship": 2}, "872f5bc8effffff": {"bar": -1, "research_institute": -1, "clinic": 1, "restaurant": 17, "library": 1, "atm": 3, "vending_machine": 6, "bench": 2, "parking_space": -1, "bank": 1, "place_of_worship": 9}, "872f5bcadffffff": {"bar": 2, "research_institute": -1, "clinic": 1, "restaurant": 11, "library": 1, "atm": -1, "vending_machine": 20, "bench": 14, "parking_space": -1, "bank": -1, "place_of_worship": 4}, "872f5b543ffffff": {"bar": -1, "research_institute": -1, "clinic": -1, "restaurant": -1, "library": -1, "atm": -1, "vending_machine": -1, "bench": -1, "parking_space": -1, "bank": -1, "place_of_worship": -1}, "872f5aaeeffffff": {"bar": -1, "research_institute": -1, "clinic": -1, "restaurant": -1, "library": -1, "atm": -1, "vending_machine": 3, "bench": 27, "parking_space": -1, "bank": -1, "place_of_worship": -1}, "872f5b42dffffff": {"bar": -1, "research_institute": -1, "clinic": -1, "restaurant": -1, "library": -1, "atm": -1, "vending_machine": -1, "bench": 1, "parking_space": -1, "bank": -1, "place_of_worship": -1}, "872f5b460ffffff": {"bar": 1, "research_institute": -1, "clinic": -1, "restaurant": 2, "library": 1, "atm": -1, "vending_machine": 1, "bench": -1, "parking_space": -1, "bank": 1, "place_of_worship": 1}, "872f5a264ffffff": {"bar": -1, "research_institute": -1, "clinic": -1, "restaurant": 6, "library": -1, "atm": -1, "vending_machine": -1, "bench": 2, "parking_space": -1, "bank": -1, "place_of_worship": 4}, "872f5bc80ffffff": {"bar": 4, "research_institute": -1, "clinic": 3, "restaurant": 63, "library": 1, "atm": 1, "vending_machine": 5, "bench": -1, "parking_space": -1, "bank": 5, "place_of_worship": 6}, "872f5bc9dffffff": {"bar": -1, "research_institute": -1, "clinic": 1, "restaurant": 12, "library": 1, "atm": -1, "vending_machine": 1, "bench": -1, "parking_space": -1, "bank": 1, "place_of_worship": 1}, "872f5a314ffffff": {"bar": -1, "research_institute": -1, "clinic": -1, "restaurant": -1, "library": -1, "atm": -1, "vending_machine": -1, "bench": -1, "parking_space": -1, "bank": -1, "place_of_worship": 13}, "872f5a332ffffff": {"bar": 4, "research_institute": -1, "clinic": -1, "restaurant": 46, "library": 1, "atm": 1, "vending_machine": -1, "bench": -1, "parking_space": -1, "bank": 3, "place_of_worship": 7}, "872f5b52dffffff": {"bar": -1, "research_institute": -1, "clinic": -1, "restaurant": 7, "library": 1, "atm": -1, "vending_machine": -1, "bench": 1, "parking_space": -1, "bank": 1, "place_of_worship": 1}, "872f5a22dffffff": {"bar": -1, "research_institute": -1, "clinic": -1, "restaurant": 2, "library": 1, "atm": -1, "vending_machine": -1, "bench": -1, "parking_space": -1, "bank": -1, "place_of_worship": 1}, "872f5b54effffff": {"bar": -1, "research_institute": 1e-16, "clinic": 1e-16, "restaurant": 1e-16, "library": 1e-16, "atm": 1e-16, "vending_machine": 1e-16, "bench": 4, "parking_space": 1e-16, "bank": 1e-16, "place_of_worship": 1}, "872f5bce2ffffff": {"bar": -1, "research_institute": 1e-16, "clinic": 2, "restaurant": 8, "library": 3, "atm": 1, "vending_machine": 21, "bench": 92, "parking_space": 1e-16, "bank": 1, "place_of_worship": 8}, "872f5aae3ffffff": {"bar": -1, "research_institute": 1e-16, "clinic": 1e-16, "restaurant": 1e-16, "library": 1e-16, "atm": 1e-16, "vending_machine": 1e-16, "bench": 2, "parking_space": 1e-16, "bank": 1e-16, "place_of_worship": 1e-16}, "87754e64dffffff": {"bar": -1, "research_institute": 1e-16, "clinic": 1e-16, "restaurant": 1e-16, "library": 1e-16, "atm": 1e-16, "vending_machine": 1e-16, "bench": 1e-16, "parking_space": 1e-16, "bank": 1e-16, "place_of_worship": 1e-16}, "872e1b56bffffff": {"bar": 30, "research_institute": 1e-16, "clinic": 7, "restaurant": 175, "library": 2, "atm": 11, "vending_machine": 42, "bench": 112, "parking_space": 1, "bank": 43, "place_of_worship": 6}, "876520d86ffffff": {"bar": 74, "research_institute": 1e-16, "clinic": 15, "restaurant": 516, "library": 1, "atm": 42, "vending_machine": 4, "bench": 10, "parking_space": 1e-16, "bank": 12, "place_of_worship": 3}, "87416a588ffffff": {"bar": 1e-16, "research_institute": 1e-16, "clinic": 1e-16, "restaurant": 1e-16, "library": 1e-16, "atm": 1e-16, "vending_machine": 1e-16, "bench": 1e-16, "parking_space": 1e-16, "bank": 1e-16, "place_of_worship": 1e-16}, "8729a1d64ffffff": {"bar": 2, "research_institute": 1e-16, "clinic": 1e-16, "restaurant": 12, "library": 1, "atm": 1, "vending_machine": 8, "bench": 1e-16, "parking_space": 1e-16, "bank": 3, "place_of_worship": 5}, "870882d70ffffff": {"bar": 1e-16, "research_institute": 1e-16, "clinic": 1e-16, "restaurant": 1e-16, "library": 1e-16, "atm": 1e-16, "vending_machine": 1e-16, "bench": 1e-16, "parking_space": 1e-16, "bank": 1e-16, "place_of_worship": 1e-16}, "871ef109cffffff": {"bar": 1e-16, "research_institute": 1e-16, "clinic": 1e-16, "restaurant": 1e-16, "library": 1e-16, "atm": 1e-16, "vending_machine": 1e-16, "bench": 1e-16, "parking_space": 1e-16, "bank": 1e-16, "place_of_worship": 1e-16}, "87195c0ecffffff": {"bar": 1e-16, "research_institute": 1e-16, "clinic": 1e-16, "restaurant": 1, "library": 1, "atm": 1, "vending_machine": 3, "bench": 4, "parking_space": 1e-16, "bank": 1e-16, "place_of_worship": 1e-16}, "872a32ca1ffffff": {"bar": 1e-16, "research_institute": 1e-16, "clinic": 1e-16, "restaurant": 1e-16, "library": 1e-16, "atm": 1e-16, "vending_machine": 1e-16, "bench": 1e-16, "parking_space": 1e-16, "bank": 1e-16, "place_of_worship": 1}, "871f1d0d4ffffff": {"bar": 1e-16, "research_institute": 1e-16, "clinic": 1e-16, "restaurant": 1e-16, "library": 1e-16, "atm": 1e-16, "vending_machine": 1e-16, "bench": 1e-16, "parking_space": 1e-16, "bank": 1e-16, "place_of_worship": 1e-16}, "872baaa59ffffff": {"bar": 1e-16, "research_institute": 1e-16, "clinic": 1e-16, "restaurant": 1e-16, "library": 1e-16, "atm": 1e-16, "vending_machine": 1e-16, "bench": 1e-16, "parking_space": 1e-16, "bank": 1e-16, "place_of_worship": 1e-16}, "87be63cd4ffffff": {"bar": 1e-16, "research_institute": 1e-16, "clinic": 7, "restaurant": 47, "library": 1e-16, "atm": 5, "vending_machine": 1e-16, "bench": 2, "parking_space": 1e-16, "bank": 8, "place_of_worship": 4}, "87be63cf3ffffff": {"bar": 1e-16, "research_institute": 1e-16, "clinic": 1e-16, "restaurant": 11, "library": 1e-16, "atm": 2, "vending_machine": 1e-16, "bench": 17, "parking_space": 1e-16, "bank": 2, "place_of_worship": 2}, "87be62366ffffff": {"bar": 1e-16, "research_institute": 1e-16, "clinic": 1e-16, "restaurant": 1e-16, "library": 1e-16, "atm": 1e-16, "vending_machine": 1e-16, "bench": 1e-16, "parking_space": 1e-16, "bank": 1e-16, "place_of_worship": 1e-16}, "87be63525ffffff": {"bar": 1e-16, "research_institute": 1e-16, "clinic": 1e-16, "restaurant": 6, "library": 1e-16, "atm": 1e-16, "vending_machine": 1e-16, "bench": 1e-16, "parking_space": 1, "bank": 1e-16, "place_of_worship": 1}, "87be63ca2ffffff": {"bar": 1e-16, "research_institute": 1e-16, "clinic": 1e-16, "restaurant": 1e-16, "library": 1e-16, "atm": 1e-16, "vending_machine": 1e-16, "bench": 12, "parking_space": 1e-16, "bank": 1e-16, "place_of_worship": 1e-16}, "87be63cb5ffffff": {"bar": 3, "research_institute": 1e-16, "clinic": 1e-16, "restaurant": 8, "library": 1e-16, "atm": 1, "vending_machine": 1e-16, "bench": 11, "parking_space": 1e-16, "bank": 1, "place_of_worship": 2}, "87be63571ffffff": {"bar": 1, "research_institute": 1e-16, "clinic": 1e-16, "restaurant": 1, "library": 1, "atm": 3, "vending_machine": 1, "bench": 38, "parking_space": 6, "bank": 1e-16, "place_of_worship": 1e-16}, "87be630a1ffffff": {"bar": 1e-16, "research_institute": 1e-16, "clinic": 1e-16, "restaurant": 1e-16, "library": 1e-16, "atm": 1e-16, "vending_machine": 2, "bench": 6, "parking_space": 10, "bank": 1e-16, "place_of_worship": 1e-16}, "87be6319effffff": {"bar": 1e-16, "research_institute": 1e-16, "clinic": 1e-16, "restaurant": 2, "library": 1e-16, "atm": 1e-16, "vending_machine": 1e-16, "bench": 8, "parking_space": 1e-16, "bank": 1e-16, "place_of_worship": 1e-16}, "87be63555ffffff": {"bar": 5, "research_institute": 1e-16, "clinic": 1e-16, "restaurant": 22, "library": 1e-16, "atm": 2, "vending_machine": 1e-16, "bench": 42, "parking_space": 3, "bank": 2, "place_of_worship": 7}, "87be63562ffffff": {"bar": 4, "research_institute": 1e-16, "clinic": 4, "restaurant": 56, "library": 1, "atm": 7, "vending_machine": 14, "bench": 102, "parking_space": 3, "bank": 5, "place_of_worship": 4}, "87be63a98ffffff": {"bar": 1e-16, "research_institute": 1e-16, "clinic": 1e-16, "restaurant": 1e-16, "library": 1e-16, "atm": 1, "vending_machine": 1e-16, "bench": 6, "parking_space": 1e-16, "bank": 4, "place_of_worship": 1e-16}, "87be63504ffffff": {"bar": 1e-16, "research_institute": 1e-16, "clinic": 1e-16, "restaurant": 1e-16, "library": 1e-16, "atm": 1e-16, "vending_machine": 1e-16, "bench": 1, "parking_space": 1e-16, "bank": 1e-16, "place_of_worship": 1e-16}, "87be63c1dffffff": {"bar": 1e-16, "research_institute": 1e-16, "clinic": 1, "restaurant": 3, "library": 1e-16, "atm": 1e-16, "vending_machine": 1e-16, "bench": 4, "parking_space": 1e-16, "bank": 3, "place_of_worship": 2}, "87be6352cffffff": {"bar": 1e-16, "research_institute": 1e-16, "clinic": 2, "restaurant": 25, "library": 1, "atm": 4, "vending_machine": 3, "bench": 7, "parking_space": 1e-16, "bank": 9, "place_of_worship": 9}, "87be6352dffffff": {"bar": 1e-16, "research_institute": 1e-16, "clinic": 1e-16, "restaurant": 1, "library": 1e-16, "atm": 1e-16, "vending_machine": 1e-16, "bench": 15, "parking_space": 1e-16, "bank": 1e-16, "place_of_worship": 3}, "87be63cdeffffff": {"bar": 1e-16, "research_institute": 1e-16, "clinic": 1e-16, "restaurant": 9, "library": 1e-16, "atm": 1e-16, "vending_machine": 1e-16, "bench": 1e-16, "parking_space": 2, "bank": 1e-16, "place_of_worship": 2}, "87be63529ffffff": {"bar": 1e-16, "research_institute": 1e-16, "clinic": 1, "restaurant": 8, "library": 1e-16, "atm": 1e-16, "vending_machine": 1e-16, "bench": 87, "parking_space": 4, "bank": 3, "place_of_worship": 5}, "87be63c32ffffff": {"bar": 1e-16, "research_institute": 1e-16, "clinic": 2, "restaurant": 13, "library": 1, "atm": 2, "vending_machine": 1e-16, "bench": 1, "parking_space": 1e-16, "bank": 1, "place_of_worship": 1}, "87be63c36ffffff": {"bar": 1e-16, "research_institute": 1e-16, "clinic": 1e-16, "restaurant": 1e-16, "library": 1e-16, "atm": 1e-16, "vending_machine": 1e-16, "bench": 34, "parking_space": 1e-16, "bank": 1e-16, "place_of_worship": 1e-16}, "87be63740ffffff": {"bar": 1e-16, "research_institute": 1e-16, "clinic": 1e-16, "restaurant": 1e-16, "library": 1e-16, "atm": 1e-16, "vending_machine": 1e-16, "bench": 4, "parking_space": 1e-16, "bank": 1e-16, "place_of_worship": 1e-16}, "87be6352effffff": {"bar": 1e-16, "research_institute": 1e-16, "clinic": 1e-16, "restaurant": 23, "library": 1e-16, "atm": 1e-16, "vending_machine": 1e-16, "bench": 7, "parking_space": 5, "bank": 2, "place_of_worship": 4}, "87be63cccffffff": {"bar": 1e-16, "research_institute": 1e-16, "clinic": 1e-16, "restaurant": 2, "library": 1e-16, "atm": 1e-16, "vending_machine": 1e-16, "bench": 1e-16, "parking_space": 1e-16, "bank": 1e-16, "place_of_worship": 1e-16}, "87be63c1effffff": {"bar": 1e-16, "research_institute": 1e-16, "clinic": 7, "restaurant": 5, "library": 1e-16, "atm": 1e-16, "vending_machine": 1e-16, "bench": 3, "parking_space": 1, "bank": 1, "place_of_worship": 1}, "87be63cf1ffffff": {"bar": 1e-16, "research_institute": 1e-16, "clinic": 1e-16, "restaurant": 2, "library": 1, "atm": 1, "vending_machine": 1e-16, "bench": 15, "parking_space": 1e-16, "bank": 1e-16, "place_of_worship": 1}, "87be63a9dffffff": {"bar": 1e-16, "research_institute": 1e-16, "clinic": 1e-16, "restaurant": 1e-16, "library": 1e-16, "atm": 1e-16, "vending_machine": 1e-16, "bench": 1, "parking_space": 1e-16, "bank": 1e-16, "place_of_worship": 1e-16}, "87be63c18ffffff": {"bar": 1e-16, "research_institute": 1e-16, "clinic": 1e-16, "restaurant": 1e-16, "library": 1e-16, "atm": 1e-16, "vending_machine": 1e-16, "bench": 2, "parking_space": 1e-16, "bank": 1e-16, "place_of_worship": 1e-16}, "87be636a3ffffff": {"bar": 1e-16, "research_institute": 1e-16, "clinic": 1, "restaurant": 1e-16, "library": 1e-16, "atm": 1e-16, "vending_machine": 1e-16, "bench": 2, "parking_space": 1e-16, "bank": 1e-16, "place_of_worship": 2}, "87be63cdcffffff": {"bar": 1e-16, "research_institute": 1e-16, "clinic": 3, "restaurant": 2, "library": 1, "atm": 1e-16, "vending_machine": 1e-16, "bench": 18, "parking_space": 1e-16, "bank": 6, "place_of_worship": 1}, "87be63ceaffffff": {"bar": 1, "research_institute": 1e-16, "clinic": 1, "restaurant": 1e-16, "library": 1e-16, "atm": 1e-16, "vending_machine": 1e-16, "bench": 1e-16, "parking_space": 1e-16, "bank": 1e-16, "place_of_worship": 1}, "87be63092ffffff": {"bar": 1e-16, "research_institute": 1e-16, "clinic": 1, "restaurant": 1e-16, "library": 1e-16, "atm": 1e-16, "vending_machine": 1e-16, "bench": 1e-16, "parking_space": 18, "bank": 2, "place_of_worship": 1e-16}, "87be630f6ffffff": {"bar": 1e-16, "research_institute": 1e-16, "clinic": 1e-16, "restaurant": 1e-16, "library": 1e-16, "atm": 1e-16, "vending_machine": 1e-16, "bench": 1e-16, "parking_space": 1e-16, "bank": 1e-16, "place_of_worship": 1e-16}, "87be61685ffffff": {"bar": 1e-16, "research_institute": 1e-16, "clinic": 1e-16, "restaurant": 1e-16, "library": 1e-16, "atm": 1e-16, "vending_machine": 1e-16, "bench": 1e-16, "parking_space": 1e-16, "bank": 1e-16, "place_of_worship": 1e-16}, "87be63c11ffffff": {"bar": 1e-16, "research_institute": 1e-16, "clinic": 1e-16, "restaurant": 1, "library": 1, "atm": 1e-16, "vending_machine": 1e-16, "bench": 1e-16, "parking_space": 1e-16, "bank": 1e-16, "place_of_worship": 3}, "87be63d1dffffff": {"bar": 1e-16, "research_institute": 1e-16, "clinic": 1e-16, "restaurant": 1e-16, "library": 1e-16, "atm": 1e-16, "vending_machine": 1e-16, "bench": 20, "parking_space": 1e-16, "bank": 1e-16, "place_of_worship": 1e-16}, "87be6356affffff": {"bar": 2, "research_institute": 1e-16, "clinic": 1e-16, "restaurant": 2, "library": 1e-16, "atm": 1e-16, "vending_machine": 1e-16, "bench": 165, "parking_space": 1, "bank": 1e-16, "place_of_worship": 1}, "87be6354cffffff": {"bar": 1e-16, "research_institute": 1e-16, "clinic": 2, "restaurant": 10, "library": 1e-16, "atm": 1e-16, "vending_machine": 1, "bench": 28, "parking_space": 7, "bank": 1e-16, "place_of_worship": 1e-16}, "87be63cd3ffffff": {"bar": 1e-16, "research_institute": 1e-16, "clinic": 1e-16, "restaurant": 5, "library": 1e-16, "atm": 1, "vending_machine": 1e-16, "bench": 13, "parking_space": 1e-16, "bank": 1e-16, "place_of_worship": 2}, "87be63d8dffffff": {"bar": 1, "research_institute": 1e-16, "clinic": 1e-16, "restaurant": 11, "library": 1, "atm": 1e-16, "vending_machine": 1e-16, "bench": 13, "parking_space": 1e-16, "bank": 6, "place_of_worship": 1e-16}, "87be63c19ffffff": {"bar": 1e-16, "research_institute": 1e-16, "clinic": 1, "restaurant": 3, "library": 1e-16, "atm": 1e-16, "vending_machine": 1e-16, "bench": 7, "parking_space": 1e-16, "bank": 1e-16, "place_of_worship": 1e-16}, "87be63d4effffff": {"bar": 1e-16, "research_institute": 1e-16, "clinic": 2, "restaurant": 9, "library": 1e-16, "atm": 1e-16, "vending_machine": 1e-16, "bench": 15, "parking_space": 1e-16, "bank": 3, "place_of_worship": 1e-16}, "87be63cd5ffffff": {"bar": 1e-16, "research_institute": 1e-16, "clinic": 1e-16, "restaurant": 4, "library": 1, "atm": 1e-16, "vending_machine": 1e-16, "bench": 6, "parking_space": 1e-16, "bank": 3, "place_of_worship": 3}, "87be63cd9ffffff": {"bar": 1e-16, "research_institute": 1e-16, "clinic": 1e-16, "restaurant": 2, "library": 1e-16, "atm": 1, "vending_machine": 1e-16, "bench": 10, "parking_space": 1, "bank": 1e-16, "place_of_worship": 1e-16}, "87be63556ffffff": {"bar": 1e-16, "research_institute": 1e-16, "clinic": 1e-16, "restaurant": 4, "library": 1e-16, "atm": 1e-16, "vending_machine": 2, "bench": 1, "parking_space": 7, "bank": 1, "place_of_worship": 2}, "87be63a85ffffff": {"bar": 1e-16, "research_institute": 1e-16, "clinic": 1, "restaurant": 2, "library": 1e-16, "atm": 1e-16, "vending_machine": 1e-16, "bench": 65, "parking_space": 6, "bank": 1e-16, "place_of_worship": 1e-16}, "87be63c84ffffff": {"bar": 1e-16, "research_institute": 1e-16, "clinic": 1e-16, "restaurant": 4, "library": 1e-16, "atm": 2, "vending_machine": 1, "bench": 6, "parking_space": 1e-16, "bank": 1e-16, "place_of_worship": 1}, "87be60735ffffff": {"bar": 1e-16, "research_institute": 1e-16, "clinic": 1e-16, "restaurant": 1e-16, "library": 1e-16, "atm": 1e-16, "vending_machine": 1e-16, "bench": 1e-16, "parking_space": 1e-16, "bank": 1e-16, "place_of_worship": 1e-16}, "87be63d5affffff": {"bar": 1e-16, "research_institute": 1e-16, "clinic": 1e-16, "restaurant": 1e-16, "library": 1e-16, "atm": 1e-16, "vending_machine": 1e-16, "bench": 39, "parking_space": 1e-16, "bank": 1e-16, "place_of_worship": 1}, "87be60730ffffff": {"bar": 1e-16, "research_institute": 1e-16, "clinic": 1e-16, "restaurant": 1e-16, "library": 1e-16, "atm": 1e-16, "vending_machine": 1e-16, "bench": 1, "parking_space": 1e-16, "bank": 1e-16, "place_of_worship": 1e-16}, "87be63cc5ffffff": {"bar": 1e-16, "research_institute": 1e-16, "clinic": 1e-16, "restaurant": 1, "library": 1e-16, "atm": 1e-16, "vending_machine": 1e-16, "bench": 8, "parking_space": 1e-16, "bank": 1e-16, "place_of_worship": 1}, "87be63cc8ffffff": {"bar": 1, "research_institute": 1e-16, "clinic": 1e-16, "restaurant": 7, "library": 1e-16, "atm": 1e-16, "vending_machine": 1e-16, "bench": 3, "parking_space": 3, "bank": 1e-16, "place_of_worship": 1}, "87be63cceffffff": {"bar": 1e-16, "research_institute": 1e-16, "clinic": 1, "restaurant": 7, "library": 1e-16, "atm": 1e-16, "vending_machine": 1e-16, "bench": 9, "parking_space": 2, "bank": 1e-16, "place_of_worship": 1}, "87be63da0ffffff": {"bar": 1, "research_institute": 1e-16, "clinic": 1e-16, "restaurant": 1, "library": 1e-16, "atm": 1e-16, "vending_machine": 1e-16, "bench": 48, "parking_space": 1e-16, "bank": 1e-16, "place_of_worship": 1e-16}, "87be63ccaffffff": {"bar": 1e-16, "research_institute": 1e-16, "clinic": 1, "restaurant": 2, "library": 1, "atm": 1e-16, "vending_machine": 1e-16, "bench": 3, "parking_space": 5, "bank": 1e-16, "place_of_worship": 3}, "87be63a99ffffff": {"bar": 1e-16, "research_institute": 1e-16, "clinic": 1e-16, "restaurant": 1e-16, "library": 1e-16, "atm": 1e-16, "vending_machine": 1e-16, "bench": 1e-16, "parking_space": 1e-16, "bank": 1e-16, "place_of_worship": 1e-16}, "87be63a8affffff": {"bar": 1e-16, "research_institute": 1e-16, "clinic": 1e-16, "restaurant": 1e-16, "library": 1e-16, "atm": 1e-16, "vending_machine": 1e-16, "bench": 2, "parking_space": 2, "bank": 1e-16, "place_of_worship": 1e-16}, "87be63cc1ffffff": {"bar": 1e-16, "research_institute": 1e-16, "clinic": 1, "restaurant": 1, "library": 1e-16, "atm": 1e-16, "vending_machine": 3, "bench": 30, "parking_space": 1e-16, "bank": 1e-16, "place_of_worship": 1}, "87be60468ffffff": {"bar": 1e-16, "research_institute": 1e-16, "clinic": 1e-16, "restaurant": 1e-16, "library": 1e-16, "atm": 1e-16, "vending_machine": 1e-16, "bench": 1e-16, "parking_space": 1e-16, "bank": 1e-16, "place_of_worship": 1e-16}, "87be6046dffffff": {"bar": 1e-16, "research_institute": 1e-16, "clinic": 1e-16, "restaurant": 1e-16, "library": 1e-16, "atm": 1e-16, "vending_machine": 1e-16, "bench": 1e-16, "parking_space": 1e-16, "bank": 1e-16, "place_of_worship": 1e-16}, "87be60719ffffff": {"bar": 1e-16, "research_institute": 1e-16, "clinic": 1e-16, "restaurant": 1e-16, "library": 1e-16, "atm": 1e-16, "vending_machine": 1e-16, "bench": 1e-16, "parking_space": 1e-16, "bank": 1e-16, "place_of_worship": 1e-16}, "87be60624ffffff": {"bar": 1e-16, "research_institute": 1e-16, "clinic": 1e-16, "restaurant": 1e-16, "library": 1e-16, "atm": 1e-16, "vending_machine": 1e-16, "bench": 1e-16, "parking_space": 1e-16, "bank": 1e-16, "place_of_worship": 1e-16}, "87be63cc4ffffff": {"bar": 1e-16, "research_institute": 1e-16, "clinic": 1, "restaurant": 1, "library": 1e-16, "atm": 1e-16, "vending_machine": 1e-16, "bench": 6, "parking_space": 1e-16, "bank": 1e-16, "place_of_worship": 2}, "87bef6d82ffffff": {"bar": 1e-16, "research_institute": 1e-16, "clinic": 1e-16, "restaurant": 1e-16, "library": 1e-16, "atm": 1e-16, "vending_machine": 1e-16, "bench": 1e-16, "parking_space": 1e-16, "bank": 1e-16, "place_of_worship": 1e-16}, "87be8d893ffffff": {"bar": 1e-16, "research_institute": 1e-16, "clinic": 1, "restaurant": 1e-16, "library": 1e-16, "atm": 1e-16, "vending_machine": 1e-16, "bench": 4, "parking_space": 1e-16, "bank": 1e-16, "place_of_worship": 1e-16}, "87be8d7b5ffffff": {"bar": 1e-16, "research_institute": 1e-16, "clinic": 1e-16, "restaurant": 1e-16, "library": 1e-16, "atm": 1e-16, "vending_machine": 1e-16, "bench": 1e-16, "parking_space": 1e-16, "bank": 1e-16, "place_of_worship": 1e-16}, "87be8d890ffffff": {"bar": 1e-16, "research_institute": 1e-16, "clinic": 1e-16, "restaurant": 1e-16, "library": 1e-16, "atm": 1e-16, "vending_machine": 1e-16, "bench": 3, "parking_space": 1e-16, "bank": 1e-16, "place_of_worship": 1}, "87be8d922ffffff": {"bar": 1e-16, "research_institute": 1e-16, "clinic": 1e-16, "restaurant": 1, "library": 1e-16, "atm": 1e-16, "vending_machine": 1e-16, "bench": 1e-16, "parking_space": 1e-16, "bank": 1e-16, "place_of_worship": 1e-16}, "87be8d123ffffff": {"bar": 1e-16, "research_institute": 1e-16, "clinic": 1e-16, "restaurant": 4, "library": 1e-16, "atm": 1e-16, "vending_machine": 2, "bench": 12, "parking_space": 1e-16, "bank": 1e-16, "place_of_worship": 2}, "87be8d892ffffff": {"bar": 1e-16, "research_institute": 1e-16, "clinic": 1e-16, "restaurant": 5, "library": 1e-16, "atm": 1e-16, "vending_machine": 1e-16, "bench": 6, "parking_space": 1e-16, "bank": 1, "place_of_worship": 1e-16}, "87bef2932ffffff": {"bar": 1e-16, "research_institute": 1e-16, "clinic": 1e-16, "restaurant": 1e-16, "library": 1e-16, "atm": 1e-16, "vending_machine": 1e-16, "bench": 1e-16, "parking_space": 1e-16, "bank": 1e-16, "place_of_worship": 1e-16}, "87be8dc6dffffff": {"bar": 1e-16, "research_institute": 1e-16, "clinic": 1e-16, "restaurant": 1e-16, "library": 1e-16, "atm": 1e-16, "vending_machine": 1e-16, "bench": 9, "parking_space": 1e-16, "bank": 1e-16, "place_of_worship": 1e-16}, "87beab38bffffff": {"bar": 1e-16, "research_institute": 1e-16, "clinic": 1, "restaurant": 1e-16, "library": 1e-16, "atm": 1e-16, "vending_machine": 1e-16, "bench": 9, "parking_space": 14, "bank": 1e-16, "place_of_worship": 1e-16}, "87beab389ffffff": {"bar": 1e-16, "research_institute": 1e-16, "clinic": 5, "restaurant": 5, "library": 1e-16, "atm": 1e-16, "vending_machine": 1e-16, "bench": 11, "parking_space": 11, "bank": 1, "place_of_worship": 1}, "87beab388ffffff": {"bar": 3, "research_institute": 1e-16, "clinic": 3, "restaurant": 21, "library": 1e-16, "atm": 1, "vending_machine": 1e-16, "bench": 20, "parking_space": 7, "bank": 1e-16, "place_of_worship": 1}, "87be8d891ffffff": {"bar": 1e-16, "research_institute": 1e-16, "clinic": 3, "restaurant": 5, "library": 1, "atm": 3, "vending_machine": 1, "bench": 5, "parking_space": 1e-16, "bank": 6, "place_of_worship": 1}, "87beab285ffffff": {"bar": 1e-16, "research_institute": 1e-16, "clinic": 2, "restaurant": 4, "library": 1e-16, "atm": 1e-16, "vending_machine": 1e-16, "bench": 1e-16, "parking_space": 1e-16, "bank": 1e-16, "place_of_worship": 1e-16}, "87be8d4d1ffffff": {"bar": 1e-16, "research_institute": 1e-16, "clinic": 1e-16, "restaurant": 1e-16, "library": 1e-16, "atm": 1e-16, "vending_machine": 1e-16, "bench": 1e-16, "parking_space": 1e-16, "bank": 1e-16, "place_of_worship": 1e-16}, "87beab2a0ffffff": {"bar": 1e-16, "research_institute": 1e-16, "clinic": 1e-16, "restaurant": 2, "library": 1e-16, "atm": 1e-16, "vending_machine": 1e-16, "bench": 1e-16, "parking_space": 1e-16, "bank": 1e-16, "place_of_worship": 1e-16}, "87be8dc6bffffff": {"bar": 1, "research_institute": 1e-16, "clinic": 1, "restaurant": 1, "library": 1, "atm": 1e-16, "vending_machine": 1e-16, "bench": 33, "parking_space": 1e-16, "bank": 1, "place_of_worship": 2}, "87beab38dffffff": {"bar": 1e-16, "research_institute": 1e-16, "clinic": 4, "restaurant": 7, "library": 1e-16, "atm": 4, "vending_machine": 1e-16, "bench": 1, "parking_space": 1e-16, "bank": 5, "place_of_worship": 1e-16}, "87beab38affffff": {"bar": 1e-16, "research_institute": 1e-16, "clinic": 1, "restaurant": 1e-16, "library": 1e-16, "atm": 1e-16, "vending_machine": 1e-16, "bench": 16, "parking_space": 1, "bank": 1e-16, "place_of_worship": 1}, "87beab310ffffff": {"bar": 1e-16, "research_institute": 1e-16, "clinic": 1e-16, "restaurant": 4, "library": 1e-16, "atm": 1e-16, "vending_machine": 1e-16, "bench": 1e-16, "parking_space": 1e-16, "bank": 1e-16, "place_of_worship": 1e-16}, "87be8d09effffff": {"bar": 1e-16, "research_institute": 1e-16, "clinic": 1e-16, "restaurant": 1e-16, "library": 1e-16, "atm": 1e-16, "vending_machine": 1e-16, "bench": 1e-16, "parking_space": 1e-16, "bank": 1e-16, "place_of_worship": 2}, "87392b000ffffff": {"bar": 1e-16, "research_institute": 1e-16, "clinic": 1e-16, "restaurant": 1e-16, "library": 1e-16, "atm": 1e-16, "vending_machine": 1e-16, "bench": 1e-16, "parking_space": 1e-16, "bank": 1e-16, "place_of_worship": 1e-16}, "87394421dffffff": {"bar": 1e-16, "research_institute": 1e-16, "clinic": 1e-16, "restaurant": 1e-16, "library": 1e-16, "atm": 1e-16, "vending_machine": 1e-16, "bench": 1e-16, "parking_space": 1e-16, "bank": 1e-16, "place_of_worship": 1e-16}, "873922731ffffff": {"bar": 8, "research_institute": 1e-16, "clinic": 2, "restaurant": 43, "library": 1e-16, "atm": 3, "vending_machine": 3, "bench": 11, "parking_space": 1e-16, "bank": 2, "place_of_worship": 1e-16}}